aiovotifier/__init__.py
aiovotifier/client.py
aiovotifier/errors.py
aiovotifier/utils.py
aiovotifier-1.0.6.dist-info/LICENSE
aiovotifier-1.0.6.dist-info/WHEEL
aiovotifier-1.0.6.dist-info/METADATA
aiovotifier-1.0.6.dist-info/RECORD
