Metadata-Version: 2.1
Name: aiovotifier
Version: 1.0.6
Summary: An asynchronous MInecraft server votifier client in Python
License: MIT
Author: Milo Weinberg
Author-email: iapetus011@gmail.com
Requires-Python: >=3.7,<4.0
Classifier: License :: OSI Approved :: MIT License
Classifier: Programming Language :: Python :: 3
Classifier: Programming Language :: Python :: 3.7
Classifier: Programming Language :: Python :: 3.8
Classifier: Programming Language :: Python :: 3.9
Classifier: Programming Language :: Python :: 3.10
Requires-Dist: cryptography (>=35.0.0,<36.0.0)
